dataconfig.py
setup.py
dataconfig.egg-info/PKG-INFO
dataconfig.egg-info/SOURCES.txt
dataconfig.egg-info/dependency_links.txt
dataconfig.egg-info/requires.txt
dataconfig.egg-info/top_level.txt